winpwn/__init__.py
winpwn/context.py
winpwn/dbg.py
winpwn/misc.py
winpwn/var.py
winpwn/win.py
winpwn/winpwn.py
allpwn-0.0.4.dist-info/METADATA
allpwn-0.0.4.dist-info/WHEEL
allpwn-0.0.4.dist-info/top_level.txt
allpwn-0.0.4.dist-info/RECORD
